{"CurrentOutagePeriods":[{"Message":"Kraków ulica Widłakowa 15, 15A, plac budowy, domek letniskowy","StartDate":"2021-11-02T08:00:00","EndDate":"2021-11-02T13:00:00","OutageType":1}],"FutureOutagePeriods":[{"Message":"Kraków ulica Skotnicka od Batalionów Chłopskich do 28, Krajobrazowa, Winnicka od 1 do 18 oraz 23, Emira od 1 do 5B oraz 12, Unruga od 25 do 31 nr nieparzyste, Batalionów Chłopskich od 1A do 3, Podole od Skotnickiej do 59 oraz 10, Domowa od Skotnickiej do 9.","StartDate":"2021-11-03T08:00:00","EndDate":"2021-11-03T15:00:00","OutageType":1},{"Message":"Kraków ulica Zalesie od 32 do 42A nr parzyste i 55 do 61 nr nieparzyste, Przemiarki od Zalesie do 20 ","StartDate":"2021-11-03T08:00:00","EndDate":"2021-11-03T16:00:00","OutageType":1},{"Message":"Kraków ul. Podbiałowa, Sawy -Calińskiego, Ostafina","StartDate":"2021-11-03T11:00:00","EndDate":"2021-11-03T14:30:00","OutageType":1},{"Message":"Kraków ulica Kuryłowicza 3 do 15 i 4 do 16, Droga Rokadowa 1, 4, Podgórki 57A do 63 i 50A do 60","StartDate":"2021-11-04T08:00:00","EndDate":"2021-11-04T15:00:00","OutageType":1},{"Message":"Kraków ulica Łanowa od 1 i 2 do 9 i 12, Kacza od 4 do 32 i od 5 do 9A, Kacza od 11 do 35, Żołnierska od Kaczej do 17 i od 19 do 31.","StartDate":"2021-11-04T08:00:00","EndDate":"2021-11-04T13:00:00","OutageType":1},{"Message":"Kraków ulica Kąpielowa 73, 75, 54A do 70, Restauracja PARKOWA, Neussera, Wypoczynkowa 2, 6, 8, Piłkarska 3 Pawilon SŁOŃCE","StartDate":"2021-11-05T08:00:00","EndDate":"2021-11-05T15:00:00","OutageType":1},{"Message":"Kraków ulica Saperów i Szwoleżerów cała, Kanonierów 6 do14, Dobra 3 do 17 i 4 do 14, oraz okolice","StartDate":"2021-11-05T08:00:00","EndDate":"2021-11-05T15:00:00","OutageType":1},{"Message":"Kraków ulica Józefa Unruga 4, 4A, 4B","StartDate":"2021-11-05T08:00:00","EndDate":"2021-11-05T12:00:00","OutageType":1},{"Message":"Kraków ulica Stepowa 12A i od 18 do 42 nr parzyste oraz 21 i od 23 do 27A i od 31 do 31F nr nieparzyste, Podgórki 36, 36A, 36B, 38, 38A, 38B","StartDate":"2021-11-08T08:00:00","EndDate":"2021-11-08T14:00:00","OutageType":1}]}