{"CurrentOutagePeriods":[{"Message":"Kraków ulica Biskupińska nr 8, 10, 10A, 12, 14 i 16","StartDate":"2022-10-19T08:00:00","EndDate":"2022-10-19T14:00:00","OutageType":1},{"Message":"Kraków ulica Tyniecka 154C, 154D","StartDate":"2022-10-19T08:00:00","EndDate":"2022-10-19T15:00:00","OutageType":1},{"Message":"Kraków ulica Szybka 37, Fatimska, od Kocmyrzowskiej w kierunku Kościoła ","StartDate":"2022-10-19T09:00:00","EndDate":"2022-10-19T14:00:00","OutageType":1}],"FutureOutagePeriods":[{"Message":"Kraków ul. Gustawa Morcinka 16E","StartDate":"2022-10-20T07:30:00","EndDate":"2022-10-20T13:00:00","OutageType":1},{"Message":"Kraków os. Na Stoku nr. 37, 38, 39, 39a, 38a, 40a, 48, 49 Kiosk ruchu ZK-1016","StartDate":"2022-10-20T08:00:00","EndDate":"2022-10-20T11:00:00","OutageType":1},{"Message":"Kraków ul. Pysocice, Narcyza Wiatra","StartDate":"2022-10-20T08:00:00","EndDate":"2022-10-20T16:00:00","OutageType":1},{"Message":"Kraków ulica Podgórki Tynieckie 88 do 120 93 do 117, ulica Dąbrowa","StartDate":"2022-10-20T09:00:00","EndDate":"2022-10-20T14:30:00","OutageType":1},{"Message":"Kraków ul. Na Wirach 30 - 64, 35, 37, oraz okolice","StartDate":"2022-10-20T09:00:00","EndDate":"2022-10-20T15:00:00","OutageType":1},{"Message":"Kraków Maciejowice kierunek potok","StartDate":"2022-10-21T08:00:00","EndDate":"2022-10-21T13:00:00","OutageType":1},{"Message":"Zielonki ul. Na Popielówkę 57 JKLM","StartDate":"2022-10-21T09:00:00","EndDate":"2022-10-21T15:00:00","OutageType":1},{"Message":"Kraków ul. Królowej Jadwigi 153,153C,153B,153A","StartDate":"2022-10-24T08:00:00","EndDate":"2022-10-24T14:00:00","OutageType":1},{"Message":"Kraków ulic Tyniecka od 124 do 132 numery parzyste oraz 132B i 132F","StartDate":"2022-10-25T08:00:00","EndDate":"2022-10-25T13:00:00","OutageType":1},{"Message":"Kraków Rynek Kleparski 12","StartDate":"2022-10-25T08:00:00","EndDate":"2022-10-25T15:00:00","OutageType":1}]}