{"CurrentOutagePeriods":[{"Message":"Kraków ulica Zelwerowicza 11 i od 13, 14 do Mochnaniec, Braterstwa Broni 29, 31 oraz od 34 do 36C, Domowa 9A, 11, Szymonowica 7, 8, 10, 11, 15, 16, 20, 21, 22, Mochnaniec od 9 do 39 oraz 12 do 30, plac budowy","StartDate":"2022-03-16T08:00:00","EndDate":"2022-03-16T14:00:00","OutageType":1},{"Message":"Kraków ulica Domowa - Place budów Złącza nr 40846, 40845, 43588","StartDate":"2022-03-16T08:00:00","EndDate":"2022-03-16T15:00:00","OutageType":1},{"Message":"Kraków ulica Bieńczycka 15 b,c,d,e","StartDate":"2022-03-16T08:00:00","EndDate":"2022-03-16T13:00:00","OutageType":1}],"FutureOutagePeriods":[{"Message":"Trzyciąż ulica Południowa i Wesoła","StartDate":"2022-03-17T08:00:00","EndDate":"2022-03-17T14:00:00","OutageType":1},{"Message":"Kraków ulica Danalówka 6 do 40 numery parzyste i 39 , 41","StartDate":"2022-03-17T08:00:00","EndDate":"2022-03-17T14:00:00","OutageType":1},{"Message":"Kraków os. Albertyńskie 25 klatka 1,2","StartDate":"2022-03-18T08:00:00","EndDate":"2022-03-18T16:00:00","OutageType":1}]}